{
  "project_info": {
    "project_number": "1023846710102",
    "project_id": "fresh-air-d6985",
    "storage_bucket": "fresh-air-d6985.appspot.com"
  },
  "client": [
    {
      "client_info": {
        "mobilesdk_app_id": "1:1023846710102:android:6615b09719e0da0d06f4f7",
        "android_client_info": {
          "package_name": "com.example.freshair"
        }
      },
      "oauth_client": [
        {
          "client_id": "1023846710102-o8p3b0oafjb11jjhp2gqafl032qjliqa.apps.googleusercontent.com",
          "client_type": 3
        }
      ],
      "api_key": [
        {
          "current_key": "AIzaSyBRd7xOx_AFLDFkjzEwSHns1WtXxr2I83M"
        }
      ],
      "services": {
        "appinvite_service": {
          "other_platform_oauth_client": [
            {
              "client_id": "1023846710102-o8p3b0oafjb11jjhp2gqafl032qjliqa.apps.googleusercontent.com",
              "client_type": 3
            }
          ]
        }
      }
    }
  ],
  "configuration_version": "1"
}